<annotation>
	<folder></folder>
	<filename>Dublin-Fire-Brigade-FLIR-Thermal-Drone-RPAS-0-5-screenshot_png_jpg.rf.bec6dfd1f18c30ec7a785e318b8c70ee.jpg</filename>
	<path>Dublin-Fire-Brigade-FLIR-Thermal-Drone-RPAS-0-5-screenshot_png_jpg.rf.bec6dfd1f18c30ec7a785e318b8c70ee.jpg</path>
	<source>
		<database>roboflow.com</database>
	</source>
	<size>
		<width>640</width>
		<height>640</height>
		<depth>3</depth>
	</size>
	<segmented>0</segmented>
	<object>
		<name>fire</name>
		<pose>Unspecified</pose>
		<truncated>0</truncated>
		<difficult>0</difficult>
		<occluded>0</occluded>
		<bndbox>
			<xmin>463</xmin>
			<xmax>504</xmax>
			<ymin>141</ymin>
			<ymax>225</ymax>
		</bndbox>
	</object>
	<object>
		<name>fire</name>
		<pose>Unspecified</pose>
		<truncated>0</truncated>
		<difficult>0</difficult>
		<occluded>0</occluded>
		<bndbox>
			<xmin>199</xmin>
			<xmax>246</xmax>
			<ymin>431</ymin>
			<ymax>535</ymax>
		</bndbox>
	</object>
	<object>
		<name>fire</name>
		<pose>Unspecified</pose>
		<truncated>0</truncated>
		<difficult>0</difficult>
		<occluded>0</occluded>
		<bndbox>
			<xmin>287</xmin>
			<xmax>303</xmax>
			<ymin>494</ymin>
			<ymax>535</ymax>
		</bndbox>
	</object>
	<object>
		<name>fire</name>
		<pose>Unspecified</pose>
		<truncated>0</truncated>
		<difficult>0</difficult>
		<occluded>0</occluded>
		<bndbox>
			<xmin>312</xmin>
			<xmax>543</xmax>
			<ymin>307</ymin>
			<ymax>639</ymax>
		</bndbox>
	</object>
</annotation>
